poetry_plugin_truststore/__init__.py
poetry_plugin_truststore/plugin.py
poetry_plugin_truststore-1.0.1.dist-info/LICENSE
poetry_plugin_truststore-1.0.1.dist-info/METADATA
poetry_plugin_truststore-1.0.1.dist-info/WHEEL
poetry_plugin_truststore-1.0.1.dist-info/entry_points.txt
poetry_plugin_truststore-1.0.1.dist-info/RECORD
