Metadata-Version: 2.3
Name: poetry-plugin-truststore
Version: 1.0.1
Summary: System certificate store support via Truststore
Author: Tander
Requires-Python: >=3.10,<4.0
Classifier: Programming Language :: Python :: 3
Classifier: Programming Language :: Python :: 3.10
Classifier: Programming Language :: Python :: 3.11
Classifier: Programming Language :: Python :: 3.12
Classifier: Programming Language :: Python :: 3.13
Requires-Dist: poetry (>=1.6.0,<3.0.0)
Requires-Dist: truststore (>=0.8.0,<2.0.0)
Project-URL: Repository, https://github.com/Tander/poetry-plugin-truststore
